rnpfind/__init__.py
rnpfind/analysis_functions.py
rnpfind/attract_data_load.py
rnpfind/bind_analysis.py
rnpfind/binding_analysis_binding_sites.py
rnpfind/colors.py
rnpfind/config.py
rnpfind/custom_binding_data.py
rnpfind/custom_data_load.py
rnpfind/data_load_functions.py
rnpfind/gene_coordinates.py
rnpfind/load_data.py
rnpfind/main.py
rnpfind/merge_annotation_funcs.py
rnpfind/over_all_corr_analysis.py
rnpfind/per_binding_site_analysis.py
rnpfind/picklify.py
rnpfind/populate_rbp_binding_sites_script.py
rnpfind/populate_trackhub.py
rnpfind/postar_data_load.py
rnpfind/pwm_scan.py
rnpfind/rbpdb_data_load.py
rnpfind/ucsc_visualize.py
rnpfind/user_input.py
rnpfind/ucsc-tools/hg38.chrom.sizes
rnpfind/ucsc-tools/linux/bedToBigBed
rnpfind/ucsc-tools/linux/wigToBigWig
rnpfind/ucsc-tools/mac-os/bedToBigBed
rnpfind/ucsc-tools/mac-os/wigToBigWig
rnpfind-1.2.6.dist-info/LICENSE
rnpfind-1.2.6.dist-info/METADATA
rnpfind-1.2.6.dist-info/WHEEL
rnpfind-1.2.6.dist-info/entry_points.txt
rnpfind-1.2.6.dist-info/top_level.txt
rnpfind-1.2.6.dist-info/RECORD
