Metadata-Version: 2.1
Name: rnpfind
Version: 1.2.6
Summary: Collect and generate RNA-RBP interaction data in various formats
Home-page: https://github.com/mnahinkhan/rnpfind
Author: Nahin Khan
Author-email: mnahinkhan@gmail.com
Classifier: Programming Language :: Python :: 3
Classifier: License :: OSI Approved :: MIT License
Classifier: Operating System :: OS Independent
Requires-Python: >=3.8
License-File: LICENSE
Requires-Dist: hgfind <2,>=1.0.0
Requires-Dist: sortedcontainers <3,>=2.4.0
Requires-Dist: trackhub <1,>=0.2.4
Requires-Dist: tqdm <5,>=4.61.2
